opticut/__init__.py
opticut/__main__.py
opticut/cs.py
opticut/optimization.py
opticut-0.0.2.dist-info/LICENSE
opticut-0.0.2.dist-info/METADATA
opticut-0.0.2.dist-info/WHEEL
opticut-0.0.2.dist-info/top_level.txt
opticut-0.0.2.dist-info/RECORD
