Metadata-Version: 2.1
Name: opticut
Version: 0.0.2
Summary: Solves the one dimensional cutting stock problem.
Home-page: https://github.com/SinaHKazemi/opticut
Author: Sina Hajikazemi
Author-email: sina.hkazemi@gmail.com
License: UNKNOWN
Project-URL: Bug Tracker, https://github.com/pypa/sampleproject/issues
Platform: UNKNOWN
Classifier: Programming Language :: Python :: 3
Classifier: License :: OSI Approved :: MIT License
Classifier: Operating System :: OS Independent
Requires-Python: >=3.6
License-File: LICENSE
